loopfunction
