Metadata-Version: 1.1
Name: loopfunction
Version: 1.1.2
Summary: A small python module for running functions in an infinite loop
Home-page: https://github.com/Zaeb0s/loop-function
Author: Christoffer Zakrisson
Author-email: christoffer_zakrisson@hotmail.com
License: MIT
Keywords: loop,function,thread,serve,forever
Platform: UNKNOWN
Classifier: Development Status :: 5 - Production/Stable
Classifier: Programming Language :: Python :: 3.5
Classifier: Operating System :: POSIX :: Linux
Classifier: License :: OSI Approved :: MIT License
